tmquery/__init__.py
tmquery/client.py
tmquery/dto/__init__.py
tmquery/dto/career_stat.py
tmquery/dto/injury.py
tmquery/dto/market_value.py
tmquery/dto/match.py
tmquery/dto/transfer.py
tmquery/query/__init__.py
tmquery/query/query.py
tmquery/query/tables.py
tmquery/spiders/__init__.py
tmquery/spiders/club.py
tmquery/spiders/competition.py
tmquery/spiders/player.py
tmquery/spiders/search.py
tmquery/utils/__init__.py
tmquery/utils/get_box.py
tmquery/utils/get_club.py
tmquery/utils/list_to_csv.py
tmquery/utils/singleton.py
tmquery/utils/strings.py
tmquery-0.0.3.dist-info/LICENSE
tmquery-0.0.3.dist-info/METADATA
tmquery-0.0.3.dist-info/WHEEL
tmquery-0.0.3.dist-info/top_level.txt
tmquery-0.0.3.dist-info/RECORD
